sedlib/__init__.py
sedlib/bol2rad.py
sedlib/catalog.py
sedlib/core.py
sedlib/helper.py
sedlib/utils.py
sedlib/version.py
sedlib/data/__init__.py
sedlib/data/temp_to_bc_coefficients.yaml
sedlib/filter/__init__.py
sedlib/filter/core.py
sedlib/filter/utils.py
sedlib/filter/data/__init__.py
sedlib/filter/data/svo_all_filter_database.pickle
sedlib/filter/data/svo_filter_catalog.pickle
sedlib/filter/data/svo_meta_data.xml
sedlib-1.0.0.dist-info/licenses/LICENSE
sedlib-1.0.0.dist-info/METADATA
sedlib-1.0.0.dist-info/WHEEL
sedlib-1.0.0.dist-info/top_level.txt
sedlib-1.0.0.dist-info/RECORD
