Metadata-Version: 2.4
Name: sedlib
Version: 1.0.0
Summary: A Python library for Spectral Energy Distribution (SED) analysis
Author-email: Oğuzhan OKUYAN <ookuyan@gmail.com>
Maintainer-email: Oğuzhan OKUYAN <ookuyan@gmail.com>
License: Apache-2.0
Project-URL: Homepage, https://github.com/ookuyan/sedlib
Project-URL: Repository, https://github.com/ookuyan/sedlib
Project-URL: Bug Tracker, https://github.com/ookuyan/sedlib/issues
Project-URL: Documentation, https://github.com/ookuyan/sedlib
Keywords: astrophysics,astronomy,spectral-energy-distribution,stellar-physics,photometry,bolometric-correction,extinction,sed-analysis
Classifier: Development Status :: 5 - Production/Stable
Classifier: Intended Audience :: Science/Research
Classifier: License :: OSI Approved :: Apache Software License
Classifier: Operating System :: OS Independent
Classifier: Programming Language :: Python :: 3
Classifier: Programming Language :: Python :: 3.8
Classifier: Programming Language :: Python :: 3.9
Classifier: Programming Language :: Python :: 3.10
Classifier: Programming Language :: Python :: 3.11
Classifier: Programming Language :: Python :: 3.12
Classifier: Topic :: Scientific/Engineering :: Astronomy
Classifier: Topic :: Scientific/Engineering :: Physics
Requires-Python: >=3.8
License-File: LICENSE
Requires-Dist: numpy>=1.20.0
Requires-Dist: scipy>=1.6.0
Requires-Dist: astroquery>=0.4.1
Requires-Dist: astropy>=4.0
Requires-Dist: dust-extinction>=1.0
Requires-Dist: beautifulsoup4>=4.9.3
Requires-Dist: lxml
Requires-Dist: pandas>=1.2.0
Requires-Dist: pyyaml>=5.4.0
Requires-Dist: requests>=2.25.0
Requires-Dist: bokeh>=2.3.0
Requires-Dist: corner>=2.2.1
Requires-Dist: ipywidgets>=7.6.0
Requires-Dist: matplotlib>=3.3.0
Requires-Dist: dill>=0.3.4
Requires-Dist: joblib>=1.0.0
Requires-Dist: psutil>=5.8.0
Requires-Dist: tqdm
Provides-Extra: dev
Requires-Dist: pytest>=7.0; extra == "dev"
Requires-Dist: pytest-cov>=3.0; extra == "dev"
Requires-Dist: black>=22.0; extra == "dev"
Requires-Dist: ruff>=0.1.0; extra == "dev"
Requires-Dist: mypy>=0.990; extra == "dev"
Requires-Dist: pre-commit>=2.20; extra == "dev"
Provides-Extra: notebook
Requires-Dist: ipython>=7.20.0; extra == "notebook"
Requires-Dist: jupyterlab; extra == "notebook"
Provides-Extra: all
Requires-Dist: sedlib[dev,notebook]; extra == "all"
Dynamic: license-file
